MANIFEST.in
README.md
requirements.txt
setup.py
dwn/__init__.py
dwn/config.py
dwn/plan.py
dwn.egg-info/PKG-INFO
dwn.egg-info/SOURCES.txt
dwn.egg-info/dependency_links.txt
dwn.egg-info/entry_points.txt
dwn.egg-info/requires.txt
dwn.egg-info/top_level.txt
dwn/../plans/altdns.yml
dwn/../plans/amass.yml
dwn/../plans/arjun.yml
dwn/../plans/binwalk.yml
dwn/../plans/cewl.yml
dwn/../plans/chisel.yml
dwn/../plans/cme.yml
dwn/../plans/commix.yml
dwn/../plans/dnsgen.yml
dwn/../plans/empire.yml
dwn/../plans/ffuf.yml
dwn/../plans/gau.yml
dwn/../plans/gobuster.yml
dwn/../plans/gowitness-report.yml
dwn/../plans/gowitness.yml
dwn/../plans/impacket.yml
dwn/../plans/metasploit.yml
dwn/../plans/netcat-reverse.yml
dwn/../plans/nginx.yml
dwn/../plans/searchsploit.yml
dwn/../plans/semgrep-sec.yml
dwn/../plans/sqlmap.yml
dwn/../plans/wpscan.yml
dwn/assets/Dockerfile
dwn/cli/__init__.py
dwn/cli/cli.py
dwn/cli/../../plans/altdns.yml
dwn/cli/../../plans/amass.yml
dwn/cli/../../plans/arjun.yml
dwn/cli/../../plans/binwalk.yml
dwn/cli/../../plans/cewl.yml
dwn/cli/../../plans/chisel.yml
dwn/cli/../../plans/cme.yml
dwn/cli/../../plans/commix.yml
dwn/cli/../../plans/dnsgen.yml
dwn/cli/../../plans/empire.yml
dwn/cli/../../plans/ffuf.yml
dwn/cli/../../plans/gau.yml
dwn/cli/../../plans/gobuster.yml
dwn/cli/../../plans/gowitness-report.yml
dwn/cli/../../plans/gowitness.yml
dwn/cli/../../plans/impacket.yml
dwn/cli/../../plans/metasploit.yml
dwn/cli/../../plans/netcat-reverse.yml
dwn/cli/../../plans/nginx.yml
dwn/cli/../../plans/searchsploit.yml
dwn/cli/../../plans/semgrep-sec.yml
dwn/cli/../../plans/sqlmap.yml
dwn/cli/../../plans/wpscan.yml
dwn/cli/../assets/Dockerfile
dwn/cli/commands/__init__.py
dwn/cli/commands/base.py
dwn/cli/commands/network.py
dwn/cli/commands/plans.py
dwn/cli/commands/../../../plans/altdns.yml
dwn/cli/commands/../../../plans/amass.yml
dwn/cli/commands/../../../plans/arjun.yml
dwn/cli/commands/../../../plans/binwalk.yml
dwn/cli/commands/../../../plans/cewl.yml
dwn/cli/commands/../../../plans/chisel.yml
dwn/cli/commands/../../../plans/cme.yml
dwn/cli/commands/../../../plans/commix.yml
dwn/cli/commands/../../../plans/dnsgen.yml
